install_playwright/__init__.py
install_playwright/py.typed
install_playwright-1.0.0.dist-info/METADATA
install_playwright-1.0.0.dist-info/WHEEL
install_playwright-1.0.0.dist-info/licenses/LICENSE
install_playwright-1.0.0.dist-info/RECORD
